my_movie_database/__init__.py
my_movie_database/app.py
my_movie_database/models/__init__.py
my_movie_database/models/movie.py
my_movie_database/operations/__init__.py
my_movie_database/operations/add.py
my_movie_database/operations/delete.py
my_movie_database/operations/list.py
my_movie_database/operations/reset.py
my_movie_database-0.1.1.data/scripts/my-movie-database
my_movie_database-0.1.1.dist-info/LICENSE
my_movie_database-0.1.1.dist-info/METADATA
my_movie_database-0.1.1.dist-info/WHEEL
my_movie_database-0.1.1.dist-info/top_level.txt
my_movie_database-0.1.1.dist-info/RECORD
